ssh_audit/__init__.py
ssh_audit/__main__.py
ssh_audit/algorithm.py
ssh_audit/algorithms.py
ssh_audit/auditconf.py
ssh_audit/banner.py
ssh_audit/builtin_policies.py
ssh_audit/dheat.py
ssh_audit/exitcodes.py
ssh_audit/fingerprint.py
ssh_audit/gextest.py
ssh_audit/globals.py
ssh_audit/hostkeytest.py
ssh_audit/kexdh.py
ssh_audit/outputbuffer.py
ssh_audit/policy.py
ssh_audit/product.py
ssh_audit/protocol.py
ssh_audit/readbuf.py
ssh_audit/software.py
ssh_audit/ssh1.py
ssh_audit/ssh1_crc32.py
ssh_audit/ssh1_kexdb.py
ssh_audit/ssh1_publickeymessage.py
ssh_audit/ssh2_kex.py
ssh_audit/ssh2_kexdb.py
ssh_audit/ssh2_kexparty.py
ssh_audit/ssh_audit.py
ssh_audit/ssh_socket.py
ssh_audit/timeframe.py
ssh_audit/utils.py
ssh_audit/writebuf.py
ssh_audit-3.3.0.dist-info/LICENSE
ssh_audit-3.3.0.dist-info/METADATA
ssh_audit-3.3.0.dist-info/WHEEL
ssh_audit-3.3.0.dist-info/entry_points.txt
ssh_audit-3.3.0.dist-info/top_level.txt
ssh_audit-3.3.0.dist-info/RECORD
