Metadata-Version: 2.1
Name: ssh-audit
Version: 3.3.0
Summary: An SSH server & client configuration security auditing tool
Home-page: https://github.com/jtesta/ssh-audit
Author: Joe Testa
Author-email: jtesta@positronsecurity.com
License: MIT
Project-URL: Source Code, https://github.com/jtesta/ssh-audit
Project-URL: Bug Tracker, https://github.com/jtesta/ssh-audit/issues
Classifier: Development Status :: 5 - Production/Stable
Classifier: Intended Audience :: Information Technology
Classifier: Intended Audience :: System Administrators
Classifier: License :: OSI Approved :: MIT License
Classifier: Operating System :: OS Independent
Classifier: Programming Language :: Python :: 3
Classifier: Programming Language :: Python :: 3.8
Classifier: Programming Language :: Python :: 3.9
Classifier: Programming Language :: Python :: 3.10
Classifier: Programming Language :: Python :: 3.11
Classifier: Programming Language :: Python :: 3.12
Classifier: Programming Language :: Python :: 3.13
Classifier: Programming Language :: Python :: Implementation :: CPython
Classifier: Programming Language :: Python :: Implementation :: PyPy
Classifier: Topic :: Security
Classifier: Topic :: Security :: Cryptography
Requires-Python: <4,>=3.8
License-File: LICENSE
